hsrcard/hsr.py
hsrcard/src/assets/background/adapt_freme_line.png
hsrcard/src/assets/background/dark.png
hsrcard/src/assets/background/default.png
hsrcard/src/assets/background/default_freme_line.png
hsrcard/src/assets/background/default_maska.png
hsrcard/src/assets/background/frame_mask.png
hsrcard/src/assets/eidolon/electro.png
hsrcard/src/assets/eidolon/fire.png
hsrcard/src/assets/eidolon/ice.png
hsrcard/src/assets/eidolon/imagunary.png
hsrcard/src/assets/eidolon/open.png
hsrcard/src/assets/eidolon/physikal.png
hsrcard/src/assets/eidolon/quantom.png
hsrcard/src/assets/eidolon/wind.png
hsrcard/src/assets/font_hsr.ttf
hsrcard/src/assets/light_cones/3_shadow_lc.png
hsrcard/src/assets/light_cones/3_star_frame_lc.png
hsrcard/src/assets/light_cones/4_shadow_lc.png
hsrcard/src/assets/light_cones/4_star_frame_lc.png
hsrcard/src/assets/light_cones/5_shadow_lc.png
hsrcard/src/assets/light_cones/5_star_frame_lc.png
hsrcard/src/assets/light_cones/blic.png
hsrcard/src/assets/light_cones/frame_lc.png
hsrcard/src/assets/light_cones/maska_lc.png
hsrcard/src/assets/light_cones/stats.png
hsrcard/src/assets/relict/background_centry.png
hsrcard/src/assets/relict/background_down.png
hsrcard/src/assets/relict/background_up.png
hsrcard/src/assets/relict/count_level.png
hsrcard/src/assets/relict/frame_centry.png
hsrcard/src/assets/relict/frame_down.png
hsrcard/src/assets/relict/frame_up.png
hsrcard/src/assets/relict/line.png
hsrcard/src/assets/relict/maska.png
hsrcard/src/assets/relict/sets_count.png
hsrcard/src/assets/stars/stars_1.png
hsrcard/src/assets/stars/stars_2.png
hsrcard/src/assets/stars/stars_3.png
hsrcard/src/assets/stars/stars_4.png
hsrcard/src/assets/stars/stars_5.png
hsrcard/src/assets/talants/adaptationt_frame.png
hsrcard/src/assets/talants/background.png
hsrcard/src/assets/talants/count.png
hsrcard/src/assets/talants/default_frame.png
hsrcard/src/assets/talants/line.png
hsrcard/src/assets/talants/main_stats.png
hsrcard/src/assets/talants/mini_stats.png
hsrcard-1.0.3.dist-info/METADATA
hsrcard-1.0.3.dist-info/WHEEL
hsrcard-1.0.3.dist-info/RECORD
