Metadata-Version: 2.1
Name: hsrcard
Version: 1.0.3
Summary: Module for generating Honkai Star Rail character cards
Home-page: https://github.com/DEViantUA/StarRailCard
Keywords: honkai,cards,generation,honkaistarraill,raill,starraill,builds
Author: None
Requires-Python: >=3.9,<4.0
Classifier: Programming Language :: Python :: 3
Classifier: Programming Language :: Python :: 3.9
Classifier: Programming Language :: Python :: 3.10
Classifier: Programming Language :: Python :: 3.11
Requires-Dist: Pillow (>=10.0.1,<11.0.0)
Requires-Dist: honkairail (>=1.1.1,<2.0.0)
Project-URL: Repository, https://github.com/DEViantUA/StarRailCard
